{
  "id": "need-to-know-podcast",
  "type": "podcast_series",
  "name": "Need to Know",
  "summary": "Journalistic UAP podcast combining current reporting, analysis, historical context, and disclosure discussion.",
  "podcastHosts": [
    "Bryce Zabel",
    "Ross Coulthart"
  ],
  "launchYear": "2021",
  "status": "Active",
  "relationships": [
    {
      "type": "discussed_topic",
      "target": "government-transparency"
    }
  ],
  "officialLinks": [
    {
      "label": "official website",
      "url": "https://www.youtube.com/channel/UCgslF1kPo4Kmv4Xrg8EyYmQ",
      "linkType": "official_website"
    },
    {
      "label": "YouTube",
      "url": "https://www.youtube.com/playlist?list=PLXdU8QbJkboeMcvUNyGpb9h6FUS9cVBti",
      "linkType": "youtube"
    },
    {
      "label": "Spotify",
      "url": "https://open.spotify.com/show/24xucCwPjcXENqwUgtKZaY",
      "linkType": "spotify"
    },
    {
      "label": "Apple Podcasts",
      "url": "https://podcasts.apple.com/us/podcast/need-to-know/id1600409359",
      "linkType": "apple_podcasts"
    }
  ],
  "referenceSources": []
}
