{
  "id": "luigi-venditelli",
  "type": "person",
  "name": "Luigi Venditelli",
  "summary": "Canadian businessman and filmmaker featured in WEAPONIZED Episode #115 discussing the production of S4: The Bob Lazar Story.",
  "relationships": [],
  "profileStatus": "Episode guest and documentary creator",
  "profileSummary": "Featured guest in WEAPONIZED Episode #115.",
  "background": "Businessman and filmmaker associated with a virtual-reality reconstruction of S4 and the documentary S4: The Bob Lazar Story.",
  "inclusionNote": "Included as the featured guest in the Episode #115 relationship-role test.",
  "profileBadge": "Media Contributor",
  "profileBadgeClass": "badge-researcher"
}
